futhark_server/__init__.py
futhark_server-1.0.0.dist-info/LICENSE
futhark_server-1.0.0.dist-info/METADATA
futhark_server-1.0.0.dist-info/WHEEL
futhark_server-1.0.0.dist-info/top_level.txt
futhark_server-1.0.0.dist-info/zip-safe
futhark_server-1.0.0.dist-info/RECORD
