Metadata-Version: 2.1
Name: futhark-server
Version: 1.0.0
Summary: Client side implementation of the Futhark server protocol
Home-page: https://github.com/diku-dk/futhark-server-python
Author: Troels Henriksen
Author-email: athas@sigkill.dk
License: ISC
Platform: UNKNOWN
Classifier: Programming Language :: Python :: 3
Classifier: License :: OSI Approved :: ISC License (ISCL)
Classifier: Operating System :: OS Independent
Requires-Python: >=3.8
License-File: LICENSE
Requires-Dist: numpy
Requires-Dist: futhark-data
